{
  "title": "Recognizing Depression from the Microbiota\u207bGut\u207bBrain Axis",
  "abstract": "Major depression is one of the leading causes of disability, morbidity, and mortality worldwide. The brain\u207bgut axis functions are disturbed, revealed by a dysfunction of the brain, immune system, endocrine system, and gut. Traditional depression treatments all target the brain, with different drugs and/or psychotherapy. Unfortunately, most of the patients have never received any treatment. Studies indicate that gut microbiota could be a direct cause for the disorder. Abnormal microbiota and the microbiota\u207bgut\u207bbrain dysfunction may cause mental disorders, while correcting these disturbance could alleviate depression. Nowadays, the gut microbiota modulation has become a hot topic in treatment research of mental disorders. Depression is closely related with the health condition of the brain\u207bgut axis, and maintaining/restoring the normal condition of gut microbiota helps in the prevention/therapy of mental disorders.",
  "relations": [
    {
      "head": "Major depression",
      "head_type": "Disease",
      "relation": "is a",
      "tail": "leading cause",
      "tail_type": "Cause"
    },
    {
      "head": "Major depression",
      "head_type": "Disease",
      "relation": "associated with",
      "tail": "disability",
      "tail_type": "Condition"
    },
    {
      "head": "Major depression",
      "head_type": "Disease",
      "relation": "associated with",
      "tail": "morbidity",
      "tail_type": "Condition"
    },
    {
      "head": "Major depression",
      "head_type": "Disease",
      "relation": "associated with",
      "tail": "mortality",
      "tail_type": "Condition"
    },
    {
      "head": "Brain\u207bgut axis",
      "head_type": "Biological System",
      "relation": "functions are disturbed",
      "tail": "dysfunction",
      "tail_type": "Condition"
    },
    {
      "head": "Brain",
      "head_type": "Organ",
      "relation": "part of",
      "tail": "brain\u207bgut axis",
      "tail_type": "Biological System"
    },
    {
      "head": "Immune system",
      "head_type": "System",
      "relation": "part of",
      "tail": "brain\u207bgut axis",
      "tail_type": "Biological System"
    },
    {
      "head": "Endocrine system",
      "head_type": "System",
      "relation": "part of",
      "tail": "brain\u207bgut axis",
      "tail_type": "Biological System"
    },
    {
      "head": "Gut",
      "head_type": "Organ",
      "relation": "part of",
      "tail": "brain\u207bgut axis",
      "tail_type": "Biological System"
    },
    {
      "head": "Traditional depression treatments",
      "head_type": "Treatment",
      "relation": "target",
      "tail": "brain",
      "tail_type": "Organ"
    },
    {
      "head": "Traditional depression treatments",
      "head_type": "Treatment",
      "relation": "include",
      "tail": "drugs",
      "tail_type": "Medication"
    },
    {
      "head": "Traditional depression treatments",
      "head_type": "Treatment",
      "relation": "include",
      "tail": "psychotherapy",
      "tail_type": "Therapy"
    },
    {
      "head": "Gut microbiota",
      "head_type": "Microbial Community",
      "relation": "could be a direct cause",
      "tail": "depression",
      "tail_type": "Disease"
    },
    {
      "head": "Abnormal microbiota",
      "head_type": "Condition",
      "relation": "may cause",
      "tail": "mental disorders",
      "tail_type": "Disease"
    },
    {
      "head": "Microbiota\u207bgut\u207bbrain dysfunction",
      "head_type": "Condition",
      "relation": "may cause",
      "tail": "mental disorders",
      "tail_type": "Disease"
    },
    {
      "head": "Correcting disturbance",
      "head_type": "Action",
      "relation": "could alleviate",
      "tail": "depression",
      "tail_type": "Disease"
    },
    {
      "head": "Gut microbiota modulation",
      "head_type": "Treatment",
      "relation": "topic in",
      "tail": "treatment research",
      "tail_type": "Research Field"
    },
    {
      "head": "Depression",
      "head_type": "Disease",
      "relation": "related to",
      "tail": "brain\u207bgut axis health",
      "tail_type": "Health Condition"
    },
    {
      "head": "Maintaining normal gut microbiota",
      "head_type": "Action",
      "relation": "helps in",
      "tail": "prevention",
      "tail_type": "Preventive Measure"
    },
    {
      "head": "Restoring normal gut microbiota",
      "head_type": "Action",
      "relation": "helps in",
      "tail": "therapy",
      "tail_type": "Therapeutic Measure"
    }
  ]
}