{
  "title": "Depletion of acetate-producing bacteria from the gut microbiota facilitates cognitive impairment through the gut-brain neural mechanism in diabetic mice.",
  "abstract": "Modification of the gut microbiota has been reported to reduce the incidence of type 1 diabetes mellitus (T1D). We hypothesized that the gut microbiota shifts might also have an effect on cognitive functions in T1D. Herein we used a non-absorbable antibiotic vancomycin to modify the gut microbiota in streptozotocin (STZ)-induced T1D mice and studied the impact of microbial changes on cognitive performances in T1D mice and its potential gut-brain neural mechanism. We found that vancomycin exposure disrupted the gut microbiome, altered host metabolic phenotypes, and facilitated cognitive impairment in T1D mice. Long-term acetate deficiency due to depletion of acetate-producing bacteria resulted in the reduction of synaptophysin (SYP) in the hippocampus as well as learning and memory impairments. Exogenous acetate supplement or fecal microbiota transplant recovered hippocampal SYP level in vancomycin-treated T1D mice, and this effect was attenuated by vagal inhibition or vagotomy. Our results demonstrate the protective role of microbiota metabolite acetate in cognitive functions and suggest long-term acetate deficiency as a risk factor of cognitive decline. Video Abstract.",
  "relations": {
    "34172093": {
      "head": "Depletion",
      "head_type": "Process",
      "relation": "facilitates",
      "tail": "cognitive impairment",
      "tail_type": "Condition"
    },
    "34172094": {
      "head": "cognitive impairment",
      "head_type": "Condition",
      "relation": "through",
      "tail": "gut-brain neural mechanism",
      "tail_type": "Mechanism"
    },
    "34172095": {
      "head": "gut-brain neural mechanism",
      "head_type": "Mechanism",
      "relation": "in",
      "tail": "diabetic mice",
      "tail_type": "Organism"
    },
    "34172096": {
      "head": "Modification",
      "head_type": "Process",
      "relation": "reported to reduce",
      "tail": "incidence",
      "tail_type": "Measure"
    },
    "34172097": {
      "head": "incidence",
      "head_type": "Measure",
      "relation": "of",
      "tail": "type 1 diabetes mellitus",
      "tail_type": "Disease"
    },
    "34172098": {
      "head": "gut microbiota shifts",
      "head_type": "Change",
      "relation": "might have effect",
      "tail": "cognitive functions",
      "tail_type": "Function"
    },
    "34172099": {
      "head": "cognitive functions",
      "head_type": "Function",
      "relation": "in",
      "tail": "T1D",
      "tail_type": "Disease"
    },
    "34172100": {
      "head": "vancomycin",
      "head_type": "Antibiotic",
      "relation": "used to modify",
      "tail": "gut microbiota",
      "tail_type": "Microbiome"
    },
    "34172101": {
      "head": "gut microbiota",
      "head_type": "Microbiome",
      "relation": "in",
      "tail": "STZ-induced T1D mice",
      "tail_type": "Organism"
    },
    "34172102": {
      "head": "STZ-induced T1D mice",
      "head_type": "Organism",
      "relation": "used to study",
      "tail": "impact",
      "tail_type": "Effect"
    },
    "34172103": {
      "head": "impact",
      "head_type": "Effect",
      "relation": "of microbial changes",
      "tail": "cognitive performances",
      "tail_type": "Function"
    },
    "34172104": {
      "head": "cognitive performances",
      "head_type": "Function",
      "relation": "in",
      "tail": "T1D mice",
      "tail_type": "Organism"
    },
    "34172105": {
      "head": "microbial changes",
      "head_type": "Change",
      "relation": "lead to",
      "tail": "cognitive impairment",
      "tail_type": "Condition"
    },
    "34172106": {
      "head": "cognitive impairment",
      "head_type": "Condition",
      "relation": "in",
      "tail": "T1D mice",
      "tail_type": "Organism"
    },
    "34172107": {
      "head": "vancomycin exposure",
      "head_type": "Exposure",
      "relation": "disrupted",
      "tail": "gut microbiome",
      "tail_type": "Microbiome"
    },
    "34172108": {
      "head": "gut microbiome",
      "head_type": "Microbiome",
      "relation": "altered",
      "tail": "host metabolic phenotypes",
      "tail_type": "Phenotype"
    },
    "34172109": {
      "head": "host metabolic phenotypes",
      "head_type": "Phenotype",
      "relation": "facilitated",
      "tail": "cognitive impairment",
      "tail_type": "Condition"
    },
    "34172110": {
      "head": "long-term acetate deficiency",
      "head_type": "Condition",
      "relation": "due to",
      "tail": "depletion of acetate-producing bacteria",
      "tail_type": "Depletion"
    },
    "34172111": {
      "head": "depletion of acetate-producing bacteria",
      "head_type": "Depletion",
      "relation": "resulted in",
      "tail": "reduction of synaptophysin",
      "tail_type": "Reduction"
    },
    "34172112": {
      "head": "reduction of synaptophysin",
      "head_type": "Reduction",
      "relation": "in",
      "tail": "hippocampus",
      "tail_type": "Anatomical Structure"
    },
    "34172113": {
      "head": "hippocampus",
      "head_type": "Anatomical Structure",
      "relation": "associated with",
      "tail": "learning and memory impairments",
      "tail_type": "Impairment"
    },
    "34172114": {
      "head": "learning and memory impairments",
      "head_type": "Impairment",
      "relation": "observed in",
      "tail": "T1D mice",
      "tail_type": "Organism"
    },
    "34172115": {
      "head": "exogenous acetate supplement",
      "head_type": "Treatment",
      "relation": "recovered",
      "tail": "hippocampal SYP level",
      "tail_type": "Physiological Parameter"
    },
    "34172116": {
      "head": "fecal microbiota transplant",
      "head_type": "Treatment",
      "relation": "recovered",
      "tail": "hippocampal SYP level",
      "tail_type": "Physiological Parameter"
    },
    "34172117": {
      "head": "hippocampal SYP level",
      "head_type": "Physiological Parameter",
      "relation": "in",
      "tail": "vancomycin-treated T1D mice",
      "tail_type": "Organism"
    },
    "34172118": {
      "head": "vagal inhibition",
      "head_type": "Intervention",
      "relation": "attenuated",
      "tail": "recovery effect",
      "tail_type": "Effect"
    },
    "34172119": {
      "head": "vagotomy",
      "head_type": "Intervention",
      "relation": "attenuated",
      "tail": "recovery effect",
      "tail_type": "Effect"
    },
    "34172120": {
      "head": "microbiota metabolite acetate",
      "head_type": "Metabolite",
      "relation": "protective role in",
      "tail": "cognitive functions",
      "tail_type": "Function"
    },
    "34172121": {
      "head": "long-term acetate deficiency",
      "head_type": "Condition",
      "relation": "risk factor of",
      "tail": "cognitive decline",
      "tail_type": "Condition"
    }
  }
}